[
  {
    "Name": "Zombie Apocalypse Survival - TEST",
    "Description": "Survive waves of zombies in this thrilling game!",
    "ExeName": "Zombie Apocalypse Survival.exe",
    "ImagePath": "images/zombie.png",
    "DownloadUrl": "https://rijankoirala.com.np/games/ZombieApocalypseSurvival.zip",
    "Status": "Available"
  },
  {
    "Name": "LAKHE",
    "Description": "Explore the horror game based in Nepali theme!",
    "ExeName": "LAKHE.exe",
    "ImagePath": "images/space.png",
    "DownloadUrl": "https://rijankoirala.com.np/games/FREETHEM.zip",
    "Status": "Upcoming"
  }
]
