[
  {
    "Name": "Zombie Apocalypse Survival",
    "Description": "Survive waves of zombies in this thrilling game!",
    "ExeName": "Zombie Apocalypse Survival.exe",
    "ImagePath": "images/zombie.png",
    "DownloadUrl": "https://rijankoirala.com.np/games/ZombieApocalypseSurvival.zip"
  },
  {
    "Name": "Space Explorer",
    "Description": "Explore the galaxy and discover new planets!",
    "ExeName": "SpaceExplorer.exe",
    "ImagePath": "images/space.png",
    "DownloadUrl": "https://rijankoirala.com.np/games/SpaceExplorer.zip"
  }
]
